cdk8s_aws_lb_controller/__init__.py
cdk8s_aws_lb_controller/py.typed
cdk8s_aws_lb_controller/_jsii/__init__.py
cdk8s_aws_lb_controller/_jsii/cdk8s-aws-lb-controller@0.2.6.jsii.tgz
cdk8s_aws_lb_controller-0.2.6.dist-info/LICENSE
cdk8s_aws_lb_controller-0.2.6.dist-info/METADATA
cdk8s_aws_lb_controller-0.2.6.dist-info/WHEEL
cdk8s_aws_lb_controller-0.2.6.dist-info/top_level.txt
cdk8s_aws_lb_controller-0.2.6.dist-info/RECORD
